FileReadTool/FileReadTool.py
FileReadTool/__init__.py
FileReadTool-1.1.dist-info/LICENSE
FileReadTool-1.1.dist-info/METADATA
FileReadTool-1.1.dist-info/WHEEL
FileReadTool-1.1.dist-info/top_level.txt
FileReadTool-1.1.dist-info/RECORD
