Metadata-Version: 2.1
Name: FileReadTool
Version: 1.1
Summary: self using package
Home-page: https://github.com/javatechy/dokr
Author: Jiaqi Zhang
Author-email: jiaqi3899@gmail.com
License: UNKNOWN
Platform: UNKNOWN
Classifier: Programming Language :: Python :: 3
Classifier: License :: OSI Approved :: MIT License
Classifier: Operating System :: OS Independent
